serious_django_services/__init__.py
serious_django_services-0.1.dist-info/LICENSE
serious_django_services-0.1.dist-info/METADATA
serious_django_services-0.1.dist-info/WHEEL
serious_django_services-0.1.dist-info/top_level.txt
serious_django_services-0.1.dist-info/RECORD
